Metadata-Version: 2.1
Name: simona-mircheva-distribution
Version: 0.1
Summary: Gaussian simona_mircheva
Home-page: UNKNOWN
License: UNKNOWN
Platform: UNKNOWN
